yatb/__init__.py
yatb/bot.py
yatb/dtypes.py
yatb/exceptions.py
yatb/polling.py
yatb-0.0.3.dist-info/entry_points.txt
yatb-0.0.3.dist-info/WHEEL
yatb-0.0.3.dist-info/METADATA
yatb-0.0.3.dist-info/RECORD
