Metadata-Version: 2.1
Name: yatb
Version: 0.0.3
Summary: Yet Another Telegram Bot implementation
License: MIT
Author: denolehov
Author-email: denolehov@gmail.com
Requires-Python: >=3.6.1,<4.0.0
Classifier: License :: OSI Approved :: MIT License
Classifier: Programming Language :: Python :: 3
Classifier: Programming Language :: Python :: 3.7
Classifier: Programming Language :: Python :: 3.8
Requires-Dist: pydantic (>=1.5.1,<2.0.0)
